zhongwen/__init__.py
zhongwen/batch_data.py
zhongwen/date.py
zhongwen/file.py
zhongwen/geopandas_tools.py
zhongwen/html.py
zhongwen/number.py
zhongwen/ocr.py
zhongwen/office_document.lark
zhongwen/office_document.py
zhongwen/pandas_tools.py
zhongwen/pdf.py
zhongwen/python_dev.py
zhongwen/test_file.py
zhongwen/text.py
zhongwen/winman.py
zhongwen/中央法規.py
zhongwen/公共設施管線圖.py
zhongwen/公有土地.py
zhongwen/國土利用調查成果圖.py
zhongwen/圖.py
zhongwen/土地稅.py
zhongwen/地址.py
zhongwen/地籍圖.py
zhongwen/地號.py
zhongwen/小狼毫輸入法.py
zhongwen/小狼毫輸入法設定檔同步服務.bat
zhongwen/庫.py
zhongwen/快取.py
zhongwen/數.py
zhongwen/文.py
zhongwen/時.py
zhongwen/時序分析.py
zhongwen/智.py
zhongwen/樂.py
zhongwen/機關單位名稱.py
zhongwen/檔.py
zhongwen/法人.py
zhongwen/法規.py
zhongwen/消防法規.py
zhongwen/程式.py
zhongwen/自動完成.py
zhongwen/花蓮縣法規.lark
zhongwen/花蓮縣法規.py
zhongwen/表.py
zhongwen/誌.py
zhongwen/資訊助理.py
zhongwen/都市計畫圖.py
zhongwen/開放街圖.py
zhongwen/電子郵件.py
zhongwen/電腦調校.py
zhongwen/cache/43fdb7c364379972d2885392bc31355e3bff1553.json
zhongwen/cache/6607838c9b089852a32d87aaa1f47cbe95935027.json
zhongwen/resource/Excel 自訂.exportedUI
zhongwen/resource/Normal.dotm
zhongwen/resource/fhopecc.xlam
zhongwen/resource/fhopecc.xlsb
zhongwen/resource/審核報告範本.docx
zhongwen/定義表/1000901建築物使用類組代碼.xlsx
zhongwen/定義表/使用牌照稅判讀管理代號.ppt
zhongwen/定義表/公文校正字典.csv
zhongwen/定義表/國土利用屬性欄位表.xlsx
zhongwen/定義表/土地利用代碼.xlsx
zhongwen/定義表/地籍圖屬性資料說明表.txt
zhongwen/定義表/建築物使用類組使用項目舉例.xlsx
zhongwen/定義表/所有權人檔(LNDT202).xls
zhongwen/定義表/持分人檔(HOUT120).xls
zhongwen/定義表/用電代碼.xlsx
zhongwen/定義表/稅地種類檔(LNDT203).xls
zhongwen/定義表/觀光資訊標準格式V1.0.pdf
zhongwen/定義表/課稅主檔(HOUT110).xls
zhongwen-5.35.14.dist-info/METADATA
zhongwen-5.35.14.dist-info/WHEEL
zhongwen-5.35.14.dist-info/RECORD
