Metadata-Version: 2.4
Name: zhongwen
Version: 5.35.14
Summary: 以中文命名之文、數、時、表及檔等處理工具集。
Project-URL: Homepage, https://github.com/fhopecc/zhongwen
Project-URL: Bug Tracker, https://github.com/fhopecc/zhongwen/issues
Author-email: fhopecc <fhopecc@gmail.com>
License: GPL-3.0-only
Classifier: License :: OSI Approved :: MIT License
Classifier: Operating System :: OS Independent
Classifier: Programming Language :: Python :: 3
Requires-Python: >=3.7
Requires-Dist: clipboard
Requires-Dist: comtypes
Requires-Dist: diskcache
Requires-Dist: lark
Requires-Dist: marisa-trie
Requires-Dist: pandas
Requires-Dist: pdf2image
Requires-Dist: pygtrans
Requires-Dist: pymupdf
Requires-Dist: pypdf2
Requires-Dist: pytesseract
Requires-Dist: python-docx
Requires-Dist: pywin32
Requires-Dist: requests
Requires-Dist: selenium
Requires-Dist: winshell
